bh_apistatus/__init__.py
bh_apistatus/result_data.py
bh_apistatus/result_status.py
bh_apistatus-1.0.0.dist-info/LICENSE
bh_apistatus-1.0.0.dist-info/METADATA
bh_apistatus-1.0.0.dist-info/WHEEL
bh_apistatus-1.0.0.dist-info/top_level.txt
bh_apistatus-1.0.0.dist-info/RECORD
