Metadata-Version: 2.1
Name: bh-apistatus
Version: 1.0.0
Summary: API Status Result
Author-email: Van Be Hai Nguyen <behai_nguyen@hotmail.com>
License: MIT License
Project-URL: repository, https://github.com/behai-nguyen/bh_apistatus
Project-URL: documentation, https://bh_apistatus.readthedocs.io/
Keywords: api,status,result
Classifier: License :: OSI Approved :: MIT License
Classifier: Programming Language :: Python
Classifier: Programming Language :: Python :: 3
Requires-Python: >=3.10
License-File: LICENSE
Requires-Dist: tomli ; python_version < "3.11"
Provides-Extra: build
Requires-Dist: build ; extra == 'build'
Requires-Dist: twine ; extra == 'build'
Provides-Extra: dev
Requires-Dist: pytest ; extra == 'dev'
Requires-Dist: coverage ; extra == 'dev'
Requires-Dist: sphinx ; extra == 'dev'
Requires-Dist: myst-parser ; extra == 'dev'
Requires-Dist: sphinx-rtd-theme ; extra == 'dev'
Requires-Dist: m2r ; extra == 'dev'
